flask_rest_toolkit/__init__.py
flask_rest_toolkit/api.py
flask_rest_toolkit/auth.py
flask_rest_toolkit/endpoint.py
flask_rest_toolkit/exceptions.py
flask_rest_toolkit/serializers.py
flask_rest_toolkit/utils.py
flask_rest_toolkit-0.0.4.dist-info/DESCRIPTION.rst
flask_rest_toolkit-0.0.4.dist-info/METADATA
flask_rest_toolkit-0.0.4.dist-info/RECORD
flask_rest_toolkit-0.0.4.dist-info/WHEEL
flask_rest_toolkit-0.0.4.dist-info/metadata.json
flask_rest_toolkit-0.0.4.dist-info/top_level.txt
flask_rest_toolkit-0.0.4.dist-info/zip-safe
