Metadata-Version: 2.0
Name: flask-rest-toolkit
Version: 0.0.4
Summary: A set of tools to create simple Flask REST web services and APIs
Home-page: https://github.com/santiagobasulto/slack-cli
Author: Santiago Basulto
Author-email: santiago@rmotr.com
License: MIT
Platform: UNKNOWN
Requires-Dist: Flask (>=0.10.1)
Requires-Dist: simplejson (>=3.8.0)
